dcmpy/__init__.py
dcmpy/maxdiff.py
dcmpy/utils.py
dcmpy-0.1.5.dist-info/METADATA
dcmpy-0.1.5.dist-info/WHEEL
dcmpy-0.1.5.dist-info/top_level.txt
dcmpy-0.1.5.dist-info/RECORD
