Metadata-Version: 2.1
Name: dcmpy
Version: 0.1.5
Summary: A discrete choice modeling package in python
Home-page: https://github.com/DataforProgress/dcmpy
Author: Nic Fishman
Author-email: njwfish@gmail.com
License: BSD 2-clause
Platform: UNKNOWN
Classifier: Development Status :: 1 - Planning
Classifier: Intended Audience :: Science/Research
Classifier: License :: OSI Approved :: BSD License
Classifier: Operating System :: POSIX :: Linux
Classifier: Programming Language :: Python :: 2
Classifier: Programming Language :: Python :: 2.7
Classifier: Programming Language :: Python :: 3
Classifier: Programming Language :: Python :: 3.4
Classifier: Programming Language :: Python :: 3.5
Requires-Dist: cvxpy
Requires-Dist: numpy
